gotify/__init__.py
gotify/async_gotify.py
gotify/errors.py
gotify/gotify.py
gotify/response_types.py
gotify-0.5.0.dist-info/LICENSE
gotify-0.5.0.dist-info/WHEEL
gotify-0.5.0.dist-info/METADATA
gotify-0.5.0.dist-info/RECORD
