Metadata-Version: 2.1
Name: gotify
Version: 0.5.0
Summary: Access your gotify server.
Author-email: d-k-bo <d-k-bo@mailbox.org>
Requires-Python: >=3.9
Classifier: Development Status :: 3 - Alpha
Classifier: Intended Audience :: Developers
Classifier: License :: OSI Approved :: MIT License
Classifier: Operating System :: OS Independent
Classifier: Programming Language :: Python :: 3 :: Only
Classifier: Programming Language :: Python :: 3.9
Classifier: Programming Language :: Python :: 3.10
Classifier: Programming Language :: Python :: 3.11
Classifier: Topic :: Home Automation
Classifier: Topic :: Utilities
Requires-Dist: httpx >= 0.22.0
Requires-Dist: websockets >= 10.3 ; extra == "stream"
Requires-Dist: pytest >= 7.1.2 ; extra == "test"
Requires-Dist: pytest-cov >= 3.0.0 ; extra == "test"
Requires-Dist: pytest-asyncio >= 0.18.3 ; extra == "test"
Requires-Dist: trycast >= 1.0 ; extra == "test"
Project-URL: Source, https://github.com/d-k-bo/python-gotify
Provides-Extra: stream
Provides-Extra: test
